[{"content":"\r\n\r\n# 直播配置正确时的表现\r\n\r\n![gif](images/麦克风有声音时的状态.gif)","cover":"","link":"直播配置正确时的表现.html","preview":"\u003cp\u003e课前在个人中心使用 \u003cstrong\u003e直播配置\u003c/strong\u003e进行调试\u003c/p\u003e\n","title":"直播配置正确时的表现"},{"content":"\r\n\r\n# 没有视频、声音\r\n\r\n建议：课前在个人中心使用 **直播配置** 是\r\n\r\n![img](images/1580279076583-6d30e006-218e-4039-9992-7b934ac2ba7f.png)\r\n\r\n![img](images/1580279077100-e97c317d-01a4-4326-a1cb-9430122a8f16.png)\r\n\r\n**需求转化**\r\n\r\n1. 麦克风自动选择有声音变化的麦克风","cover":"/images/1580279076583-6d30e006-218e-4039-9992-7b934ac2ba7f.png","link":"没有视频、声音.html","preview":"\u003cp\u003e课前在个人中心使用 \u003cstrong\u003e直播配置\u003c/strong\u003e进行调试\u003c/p\u003e\n","title":"没有视频、声音"}]